{
  "symbol": "QCOM",
  "predictionDay": [
    {
      "Open": 145.66000366210938,
      "High": 146.97999572753906,
      "Low": 144.60000610351562,
      "Volume": 6214900,
      "Dividends": 0.0,
      "Stock Splits": 0.0,
      "Date": "2025-05-10 00:00:00",
      "Close": 244.99
    }
  ],
  "predictionWeek": [
    {
      "Open": 145.66000366210938,
      "High": 146.97999572753906,
      "Low": 144.60000610351562,
      "Volume": 6214900,
      "Dividends": 0.0,
      "Stock Splits": 0.0,
      "Date": "2025-05-16 00:00:00",
      "Close": 300.37
    }
  ],
  "predictionMonth": [
    {
      "Open": 145.66000366210938,
      "High": 146.97999572753906,
      "Low": 144.60000610351562,
      "Volume": 6214900,
      "Dividends": 0.0,
      "Stock Splits": 0.0,
      "Date": "2025-06-09 00:00:00",
      "Close": 333.38
    }
  ],
  "predictionYear": [
    {
      "Open": 145.66000366210938,
      "High": 146.97999572753906,
      "Low": 144.60000610351562,
      "Volume": 6214900,
      "Dividends": 0.0,
      "Stock Splits": 0.0,
      "Date": "2026-05-09 00:00:00",
      "Close": 337.68
    }
  ]
}